django_livereload-1.7.dist-info/DESCRIPTION.rst
django_livereload-1.7.dist-info/METADATA
django_livereload-1.7.dist-info/RECORD
django_livereload-1.7.dist-info/WHEEL
django_livereload-1.7.dist-info/metadata.json
django_livereload-1.7.dist-info/top_level.txt
livereload/__init__.py
livereload/middleware.py
livereload/management/__init__.py
livereload/management/commands/__init__.py
livereload/management/commands/runserver.py
