Metadata-Version: 1.1
Name: django-livereload
Version: 1.7
Summary: LiveReload with the Django development server
Home-page: https://github.com/Fantomas42/django-livereload
Author: Fantomas42
Author-email: fantomas42@gmail.com
License: BSD License
Keywords: django,server,runserver,livereload
Platform: UNKNOWN
Classifier: Framework :: Django
Classifier: Environment :: Web Environment
Classifier: Programming Language :: Python
Classifier: Programming Language :: Python :: 3
Classifier: Intended Audience :: Developers
Classifier: Operating System :: OS Independent
Classifier: License :: OSI Approved :: BSD License
Classifier: Topic :: Software Development :: Libraries :: Python Modules
